complice/__init__.py
complice/complice.py
complice_api-0.1.dist-info/LICENSE
complice_api-0.1.dist-info/METADATA
complice_api-0.1.dist-info/WHEEL
complice_api-0.1.dist-info/top_level.txt
complice_api-0.1.dist-info/RECORD
